LICENSE
MANIFEST.in
README.rst
setup.py
django_tethys_datasets.egg-info/PKG-INFO
django_tethys_datasets.egg-info/SOURCES.txt
django_tethys_datasets.egg-info/dependency_links.txt
django_tethys_datasets.egg-info/requires.txt
django_tethys_datasets.egg-info/top_level.txt
tethys_datasets/__init__.py
tethys_datasets/admin.py
tethys_datasets/apps.py
tethys_datasets/base.py
tethys_datasets/models.py
tethys_datasets/urls.py
tethys_datasets/utilities.py
tethys_datasets/views.py
tethys_datasets/migrations/0001_initial.py
tethys_datasets/migrations/0002_auto_20150119_1756.py
tethys_datasets/migrations/0003_spatialdatasetservice.py
tethys_datasets/migrations/__init__.py
tethys_datasets/static/tethys_datasets/css/tethys_datasets.css
tethys_datasets/static/tethys_datasets/js/tethys_datasets.js
tethys_datasets/static/tethys_datasets/less/tethys_datasets.less
tethys_datasets/templates/tethys_datasets/base.html
tethys_datasets/templates/tethys_datasets/home.html
tethys_datasets/tests/__init__.py
tethys_datasets/tests/ckan_engine_tests.py
tethys_datasets/tests/support/upload_test.txt