Metadata-Version: 1.1
Name: django-tethys-datasets
Version: 1.0.0
Summary: An app to enable provide access to dataset storage for apps.
Home-page: UNKNOWN
Author: Nathan Swain
Author-email: nathan.swain@byu.net
License: BSD 2-Clause License
Platform: UNKNOWN
Classifier: Environment :: Web Environment
Classifier: Framework :: Django
Classifier: Intended Audience :: Developers
Classifier: License :: OSI Approved :: BSD License
Classifier: Operating System :: OS Independent
Classifier: Programming Language :: Python
Classifier: Programming Language :: Python :: 2
Classifier: Programming Language :: Python :: 2.7
Classifier: Topic :: Internet :: WWW/HTTP
Classifier: Topic :: Internet :: WWW/HTTP :: Dynamic Content
